{"kpis":{"costeActual":420.0,"costeEco":163.8,"ahorroNeto":256.2,"co2EvitadoKg":37.55,"porcentajeOcupacionSinEco":20,"porcentajeOcupacionConEco":72},"graficos":{"rutasLanzadas":{"sinEco":7,"conEco":3},"emisionesDiarias":{"dias":["L","M","X","J","V","S","D"],"acumuladoActual":[12,25,38,48,60,72,84],"acumuladoEco":[4,12,12,10,11,24,36]},"costeDiario":{"dias":["L","M","X","J","V","S","D"],"acumuladoActual":[60,120,180,240,300,360,420],"acumuladoEco":[0,0,60,60,60,120,180]}},"tablaRoi":[{"zona":"28931 Móstoles","rutasAhorradas":1.0,"ahorroEuros":51,"co2Evitado":7,"roi":"Alto"},{"zona":"28001 Madrid","rutasAhorradas":2.0,"ahorroEuros":51,"co2Evitado":7,"roi":"Alto"},{"zona":"08001 Barcelona","rutasAhorradas":1.5,"ahorroEuros":51,"co2Evitado":7,"roi":"Alto"},{"zona":"41001 Sevilla","rutasAhorradas":1.0,"ahorroEuros":51,"co2Evitado":7,"roi":"Medio"},{"zona":"46001 Valencia","rutasAhorradas":1.0,"ahorroEuros":51,"co2Evitado":7,"roi":"Alto"}],"historicoProyecciones":[{"periodo":"1 Semana","dias":7,"ahorroEuros":256.2,"co2EvitadoKg":37.55,"paquetesOptimizados":33},{"periodo":"1 Mes","dias":30,"ahorroEuros":1097.8,"co2EvitadoKg":154.37,"paquetesOptimizados":191},{"periodo":"1 Año","dias":365,"ahorroEuros":13005.0,"co2EvitadoKg":1986.61,"paquetesOptimizados":1939}]}